sapgui/__init__.py
sapgui/sapgui.py
sapgui/sapguicode.py
sapgui-0.0.18.dist-info/METADATA
sapgui-0.0.18.dist-info/WHEEL
sapgui-0.0.18.dist-info/top_level.txt
sapgui-0.0.18.dist-info/RECORD
