Metadata-Version: 2.1
Name: sapgui
Version: 0.0.18
Summary: Python package to control SAP GUI scripting.
Author: Piotr Kocemba
Author-email: <KocembaPiotr@gmail.com>
Keywords: python,sap
Classifier: Development Status :: 3 - Alpha
Classifier: Intended Audience :: Education
Classifier: Programming Language :: Python :: 2
Classifier: Programming Language :: Python :: 3
Classifier: Operating System :: MacOS :: MacOS X
Classifier: Operating System :: Microsoft :: Windows
